task3/ram.sv
module ram #(parameter ADDRESS_WIDTH = 9, DATA_WIDTH = 8)
(input logic clk,
 input logic wr_en,
 input logic rd_en,
 input logic[ADDRESS_WIDTH-1:0] wr_addr,
 input logic[ADDRESS_WIDTH-1:0] rd_addr,
 input logic[DATA_WIDTH-1:0] din,
 output logic[DATA_WIDTH-1:0] dout);

    logic [DATA_WIDTH-1:0] ram_array[2**ADDRESS_WIDTH - 1:0];

    always_ff @(posedge clk) begin
        if (wr_en)
            ram_array[wr_addr] <= din;
        if (rd_en)
            dout <= ram_array[rd_addr];
    end

endmodule

task3/counter.sv
module counter #(parameter WIDTH = 9)
(input logic clk,
 input logic en,
 input logic rst,
 output logic[WIDTH-1:0] count);

    always_ff @(posedge clk) begin
        if (rst)
            count <= {WIDTH{1'b0}};
        else if (en)
            count <= count + {{WIDTH-1{1'b0}}, en};
    end

endmodule

task3/sigdelay.sv
module sigdelay
(input logic clk,
 input logic rst,
 input logic wr,
 input logic rd,
 input logic[7:0] offset,
 input logic[7:0] mic_signal,
 output logic[7:0] delayed_signal);

    logic[8:0] write_addr;
    logic[8:0] read_addr;

    counter myCounter(clk, wr, rst, write_addr);
    ram myRam(clk, wr, rd, write_addr, read_addr, mic_signal, delayed_signal);

    always_comb begin
        read_addr = write_addr - {0, {8{offset}}}; // Play back from an earlier address
    end

endmodule

task3/sigdelay.vcd
$version Generated by VerilatedVcd $end
$date Wed Oct 26 23:00:32 2022 $end
$timescale 1ps $end

 $scope module TOP $end
  $var wire  1 # clk $end
  $var wire  8 ) delayed_signal [7:0] $end
  $var wire  8 ( mic_signal [7:0] $end
  $var wire  8 ' offset [7:0] $end
  $var wire  1 & rd $end
  $var wire  1 $ rst $end
  $var wire  1 % wr $end
  $scope module sigdelay $end
   $var wire  1 # clk $end
   $var wire  8 ) delayed_signal [7:0] $end
   $var wire  8 ( mic_signal [7:0] $end
   $var wire  8 ' offset [7:0] $end
   $var wire  1 & rd $end
   $var wire  9 + read_addr [8:0] $end
   $var wire  1 $ rst $end
   $var wire  1 % wr $end
   $var wire  9 * write_addr [8:0] $end
   $scope module myCounter $end
    $var wire 32 , WIDTH [31:0] $end
    $var wire  1 # clk $end
    $var wire  9 * count [8:0] $end
    $var wire  1 % en $end
    $var wire  1 $ rst $end
   $upscope $end
   $scope module myRam $end
    $var wire 32 , ADDRESS_WIDTH [31:0] $end
    $var wire 32 - DATA_WIDTH [31:0] $end
    $var wire  1 # clk $end
    $var wire  8 ( din [7:0] $end
    $var wire  8 ) dout [7:0] $end
    $var wire  9 + rd_addr [8:0] $end
    $var wire  1 & rd_en $end
    $var wire  9 * wr_addr [8:0] $end
    $var wire  1 % wr_en $end
   $upscope $end
  $upscope $end
 $upscope $end
$enddefinitions $end


#0
1#
0$
1%
1&
b01000000 '
b00000000 (
b00000000 )
b000000000 *
b111000000 +
b00000000000000000000000000001001 ,
b00000000000000000000000000001000 -
#1
0#
#2
1#
b00110011 '
b00111101 (
b000000001 *
b011001110 +
#3
0#
#4
1#
b00101110 (
b000000010 *
b011001111 +
#5
0#
#6
1#
b000000011 *
b011010000 +
#7
0#
#8
1#
b00101111 (
b000000100 *
b011010001 +
#9
0#
#10
1#
b00110100 (
b000000101 *
b011010010 +
#11
0#
#12
1#
b00111010 (
b000000110 *
b011010011 +
#13
0#
#14
1#
b01001001 (
b000000111 *
b011010100 +
#15
0#
#16
1#
b01011001 (
b000001000 *
b011010101 +
#17
0#
#18
1#
b01101010 (
b000001001 *
b011010110 +
#19
0#
#20
1#
b01111011 (
b000001010 *
b011010111 +
#21
0#
#22
1#
b10001010 (
b000001011 *
b011011000 +
#23
0#
#24
1#
b10011010 (
b000001100 *
b011011001 +
#25
0#
#26
1#
b10100011 (
b000001101 *
b011011010 +
#27
0#
#28
1#
b10101010 (
b000001110 *
b011011011 +
#29
0#
#30
1#
b000001111 *
b011011100 +
#31
0#
#32
1#
b10101000 (
b000010000 *
b011011101 +
#33
0#
#34
1#
b10011101 (
b000010001 *
b011011110 +
#35
0#
#36
1#
b10001011 (
b000010010 *
b011011111 +
#37
0#
#38
1#
b01110111 (
b000010011 *
b011100000 +
#39
0#
#40
1#
b01011111 (
b000010100 *
b011100001 +
#41
0#
#42
1#
b01001101 (
b000010101 *
b011100010 +
#43
0#
#44
1#
b00111011 (
b000010110 *
b011100011 +
#45
0#
#46
1#
b00110100 (
b000010111 *
b011100100 +
#47
0#
#48
1#
b00101101 (
b000011000 *
b011100101 +
#49
0#
#50
1#
b000011001 *
b011100110 +
#51
0#
#52
1#
b00110001 (
b000011010 *
b011100111 +
#53
0#
#54
1#
b00110110 (
b000011011 *
b011101000 +
#55
0#
#56
1#
b01000001 (
b000011100 *
b011101001 +
#57
0#
#58
1#
b01010000 (
b000011101 *
b011101010 +
#59
0#
#60
1#
b01011111 (
b000011110 *
b011101011 +
#61
0#
#62
1#
b01101111 (
b000011111 *
b011101100 +
#63
0#
#64
1#
b10000100 (
b000100000 *
b011101101 +
#65
0#
#66
1#
b10010000 (
b000100001 *
b011101110 +
#67
0#
#68
1#
b10011101 (
b000100010 *
b011101111 +
#69
0#
#70
1#
b10100101 (
b000100011 *
b011110000 +
#71
0#
#72
1#
b10101010 (
b000100100 *
b011110001 +
#73
0#
#74
1#
b10101100 (
b000100101 *
b011110010 +
#75
0#
#76
1#
b10100010 (
b000100110 *
b011110011 +
#77
0#
#78
1#
b10010110 (
b000100111 *
b011110100 +
#79
0#
#80
1#
b10000011 (
b000101000 *
b011110101 +
#81
0#
#82
1#
b01110000 (
b000101001 *
b011110110 +
#83
0#
#84
1#
b01010110 (
b000101010 *
b011110111 +
#85
0#
#86
1#
b01000111 (
b000101011 *
b011111000 +
#87
0#
#88
1#
b00111000 (
b000101100 *
b011111001 +
#89
0#
#90
1#
b00110000 (
b000101101 *
b011111010 +
#91
0#
#92
1#
b00101101 (
b000101110 *
b011111011 +
#93
0#
#94
1#
b00101100 (
b000101111 *
b011111100 +
#95
0#
#96
1#
b00110001 (
b000110000 *
b011111101 +
#97
0#
#98
1#
b00111010 (
b000110001 *
b011111110 +
#99
0#
#100
1#
b01000101 (
b000110010 *
b011111111 +
#101
0#
#102
1#
b01010011 (
b000110011 *
b100000000 +
#103
0#
#104
1#
b01100101 (
b000110100 *
b100000001 +
#105
0#
#106
1#
b01110100 (
b000110101 *
b100000010 +
#107
0#
#108
1#
b10000111 (
b000110110 *
b100000011 +
#109
0#
#110
1#
b10010111 (
b000110111 *
b100000100 +
#111
0#
#112
1#
b10100001 (
b000111000 *
b100000101 +
#113
0#
#114
1#
b10100111 (
b000111001 *
b100000110 +
#115
0#
#116
1#
b10101101 (
b000111010 *
b100000111 +
#117
0#
#118
1#
b10101011 (
b000111011 *
b100001000 +
#119
0#
#120
1#
b10100001 (
b000111100 *
b100001001 +
#121
0#
#122
1#
b10010001 (
b000111101 *
b100001010 +
#123
0#
#124
1#
b01111011 (
b000111110 *
b100001011 +
#125
0#
#126
1#
b01101010 (
b000111111 *
b100001100 +
#127
0#
#128
1#
b01010000 (
b001000000 *
b100001101 +
#129
0#
#130
1#
b01000010 (
b001000001 *
b100001110 +
#131
0#
#132
1#
b00110110 (
b001000010 *
b100001111 +
#133
0#
#134
1#
b00101110 (
b001000011 *
b100010000 +
#135
0#
#136
1#
b00101101 (
b001000100 *
b100010001 +
#137
0#
#138
1#
b001000101 *
b100010010 +
#139
0#
#140
1#
b00110010 (
b001000110 *
b100010011 +
#141
0#
#142
1#
b00111100 (
b001000111 *
b100010100 +
#143
0#
#144
1#
b01001001 (
b001001000 *
b100010101 +
#145
0#
#146
1#
b01010111 (
b001001001 *
b100010110 +
#147
0#
#148
1#
b01101000 (
b001001010 *
b100010111 +
#149
0#
#150
1#
b01111100 (
b001001011 *
b100011000 +
#151
0#
#152
1#
b10001001 (
b001001100 *
b100011001 +
#153
0#
#154
1#
b10011001 (
b001001101 *
b100011010 +
#155
0#
#156
1#
b10100100 (
b001001110 *
b100011011 +
#157
0#
#158
1#
b10101000 (
b001001111 *
b100011100 +
#159
0#
#160
1#
b10101110 (
b001010000 *
b100011101 +
#161
0#
#162
1#
b10101001 (
b001010001 *
b100011110 +
#163
0#
#164
1#
b10011110 (
b001010010 *
b100011111 +
#165
0#
#166
1#
b10001110 (
b001010011 *
b100100000 +
#167
0#
#168
1#
b01111010 (
b001010100 *
b100100001 +
#169
0#
#170
1#
b01100010 (
b001010101 *
b100100010 +
#171
0#
#172
1#
b01001110 (
b001010110 *
b100100011 +
#173
0#
#174
1#
b00111100 (
b001010111 *
b100100100 +
#175
0#
#176
1#
b00110011 (
b001011000 *
b100100101 +
#177
0#
#178
1#
b00101111 (
b001011001 *
b100100110 +
#179
0#
#180
1#
b00101101 (
b001011010 *
b100100111 +
#181
0#
#182
1#
b00101111 (
b001011011 *
b100101000 +
#183
0#
#184
1#
b00110110 (
b001011100 *
b100101001 +
#185
0#
#186
1#
b00111101 (
b001011101 *
b100101010 +
#187
0#
#188
1#
b01001011 (
b001011110 *
b100101011 +
#189
0#
#190
1#
b01011010 (
b001011111 *
b100101100 +
#191
0#
#192
1#
b01101011 (
b001100000 *
b100101101 +
#193
0#
#194
1#
b01111111 (
b001100001 *
b100101110 +
#195
0#
#196
1#
b10001110 (
b001100010 *
b100101111 +
#197
0#
#198
1#
b10011110 (
b001100011 *
b100110000 +
#199
0#
#200
1#
b10100001 (
b001100100 *
b100110001 +
#201
0#
#202
1#
b10101001 (
b001100101 *
b100110010 +
#203
0#
#204
1#
b10101010 (
b001100110 *
b100110011 +
#205
0#
#206
1#
b10100011 (
b001100111 *
b100110100 +
#207
0#
#208
1#
b10011001 (
b001101000 *
b100110101 +
#209
0#
#210
1#
b10000111 (
b001101001 *
b100110110 +
#211
0#
#212
1#
b01110000 (
b001101010 *
b100110111 +
#213
0#
#214
1#
b01011000 (
b001101011 *
b100111000 +
#215
0#
#216
1#
b01000111 (
b001101100 *
b100111001 +
#217
0#
#218
1#
b00111001 (
b001101101 *
b100111010 +
#219
0#
#220
1#
b00101111 (
b001101110 *
b100111011 +
#221
0#
#222
1#
b00101100 (
b001101111 *
b100111100 +
#223
0#
#224
1#
b00101010 (
b001110000 *
b100111101 +
#225
0#
#226
1#
b00101101 (
b001110001 *
b100111110 +
#227
0#
#228
1#
b00110100 (
b001110010 *
b100111111 +
#229
0#
#230
1#
b00111111 (
b001110011 *
b101000000 +
#231
0#
#232
1#
b01010001 (
b001110100 *
b101000001 +
#233
0#
#234
1#
b01011111 (
b001110101 *
b101000010 +
#235
0#
#236
1#
b01110100 (
b001110110 *
b101000011 +
#237
0#
#238
1#
b10000010 (
b001110111 *
b101000100 +
#239
0#
#240
1#
b10010001 (
b001111000 *
b101000101 +
#241
0#
#242
1#
b10011110 (
b001111001 *
b101000110 +
#243
0#
#244
1#
b10100110 (
b001111010 *
b101000111 +
#245
0#
#246
1#
b10101010 (
b001111011 *
b101001000 +
#247
0#
#248
1#
b10101001 (
b001111100 *
b101001001 +
#249
0#
#250
1#
b10011111 (
b001111101 *
b101001010 +
#251
0#
#252
1#
b10010000 (
b001111110 *
b101001011 +
#253
0#
#254
1#
b01111111 (
b001111111 *
b101001100 +
#255
0#
#256
1#
b01100111 (
b010000000 *
b101001101 +
#257
0#
#258
1#
b01010000 (
b010000001 *
b101001110 +
#259
0#
#260
1#
b01000011 (
b010000010 *
b101001111 +
#261
0#
#262
1#
b00110101 (
b010000011 *
b101010000 +
#263
0#
#264
1#
b00101110 (
b010000100 *
b101010001 +
#265
0#
#266
1#
b00101011 (
b010000101 *
b101010010 +
#267
0#
#268
1#
b00101100 (
b010000110 *
b101010011 +
#269
0#
#270
1#
b00110001 (
b010000111 *
b101010100 +
#271
0#
#272
1#
b00111001 (
b010001000 *
b101010101 +
#273
0#
#274
1#
b01001000 (
b010001001 *
b101010110 +
#275
0#
#276
1#
b01010110 (
b010001010 *
b101010111 +
#277
0#
#278
1#
b01100111 (
b010001011 *
b101011000 +
#279
0#
#280
1#
b01111001 (
b010001100 *
b101011001 +
#281
0#
#282
1#
b10000111 (
b010001101 *
b101011010 +
#283
0#
#284
1#
b10010111 (
b010001110 *
b101011011 +
#285
0#
#286
1#
b10011111 (
b010001111 *
b101011100 +
#287
0#
#288
1#
b10101000 (
b010010000 *
b101011101 +
#289
0#
#290
1#
b10101010 (
b010010001 *
b101011110 +
#291
0#
#292
1#
b10100101 (
b010010010 *
b101011111 +
#293
0#
#294
1#
b10011011 (
b010010011 *
b101100000 +
#295
0#
#296
1#
b10001001 (
b010010100 *
b101100001 +
#297
0#
#298
1#
b01110110 (
b010010101 *
b101100010 +
#299
0#
#300
1#
b01100011 (
b010010110 *
b101100011 +
#301
0#
#302
1#
b01001100 (
b010010111 *
b101100100 +
#303
0#
#304
1#
b00111101 (
b010011000 *
b101100101 +
#305
0#
#306
1#
b00110101 (
b010011001 *
b101100110 +
#307
0#
#308
1#
b00101101 (
b010011010 *
b101100111 +
#309
0#
#310
1#
b010011011 *
b101101000 +
#311
0#
#312
1#
b00101111 (
b010011100 *
b101101001 +
#313
0#
#314
1#
b00110110 (
b010011101 *
b101101010 +
#315
0#
#316
1#
b01000000 (
b010011110 *
b101101011 +
#317
0#
#318
1#
b01001101 (
b010011111 *
b101101100 +
#319
0#
#320
1#
b01011001 (
b010100000 *
b101101101 +
#321
0#
#322
1#
b01101110 (
b010100001 *
b101101110 +
#323
0#
#324
1#
b01111111 (
b010100010 *
b101101111 +
#325
0#
#326
1#
b10001111 (
b010100011 *
b101110000 +
#327
0#
#328
1#
b10011101 (
b010100100 *
b101110001 +
#329
0#
#330
1#
b10100101 (
b010100101 *
b101110010 +
#331
0#
#332
1#
b10101010 (
b010100110 *
b101110011 +
#333
0#
#334
1#
b10101001 (
b010100111 *
b101110100 +
#335
0#
#336
1#
b10100101 (
b010101000 *
b101110101 +
#337
0#
#338
1#
b10010101 (
b010101001 *
b101110110 +
#339
0#
#340
1#
b10000110 (
b010101010 *
b101110111 +
#341
0#
#342
1#
b01110000 (
b010101011 *
b101111000 +
#343
0#
#344
1#
b01011001 (
b010101100 *
b101111001 +
#345
0#
#346
1#
b01001000 (
b010101101 *
b101111010 +
#347
0#
#348
1#
b00111011 (
b010101110 *
b101111011 +
#349
0#
#350
1#
b00110000 (
b010101111 *
b101111100 +
#351
0#
#352
1#
b00101100 (
b010110000 *
b101111101 +
#353
0#
#354
1#
b00101101 (
b010110001 *
b101111110 +
#355
0#
#356
1#
b00110001 (
b010110010 *
b101111111 +
#357
0#
#358
1#
b00111001 (
b010110011 *
b110000000 +
#359
0#
#360
1#
b01000100 (
b010110100 *
b110000001 +
#361
0#
#362
1#
b01010101 (
b010110101 *
b110000010 +
#363
0#
#364
1#
b01100100 (
b010110110 *
b110000011 +
#365
0#
#366
1#
b01110110 (
b010110111 *
b110000100 +
#367
0#
#368
1#
b10000100 (
b010111000 *
b110000101 +
#369
0#
#370
1#
b10010101 (
b010111001 *
b110000110 +
#371
0#
#372
1#
b10100011 (
b010111010 *
b110000111 +
#373
0#
#374
1#
b10101001 (
b010111011 *
b110001000 +
#375
0#
#376
1#
b10101111 (
b010111100 *
b110001001 +
#377
0#
#378
1#
b10101000 (
b010111101 *
b110001010 +
#379
0#
#380
1#
b10100011 (
b010111110 *
b110001011 +
#381
0#
#382
1#
b10010011 (
b010111111 *
b110001100 +
#383
0#
#384
1#
b01111101 (
b011000000 *
b110001101 +
#385
0#
#386
1#
b01101001 (
b011000001 *
b110001110 +
#387
0#
#388
1#
b01010011 (
b011000010 *
b110001111 +
#389
0#
#390
1#
b01000010 (
b011000011 *
b110010000 +
#391
0#
#392
1#
b00110101 (
b011000100 *
b110010001 +
#393
0#
#394
1#
b00101110 (
b011000101 *
b110010010 +
#395
0#
#396
1#
b00101011 (
b011000110 *
b110010011 +
#397
0#
#398
1#
b00101111 (
b011000111 *
b110010100 +
#399
0#
#400
1#
b00110100 (
b011001000 *
b110010101 +
#401
0#
#402
1#
b00111011 (
b011001001 *
b110010110 +
#403
0#
#404
1#
b01001011 (
b011001010 *
b110010111 +
#405
0#
#406
1#
b01011001 (
b011001011 *
b110011000 +
#407
0#
#408
1#
b01101010 (
b011001100 *
b110011001 +
#409
0#
#410
1#
b01111100 (
b011001101 *
b110011010 +
#411
0#
#412
1#
b10001100 (
b011001110 *
b110011011 +
#413
0#
#414
1#
b10011011 (
b011001111 *
b110011100 +
#415
0#
#416
1#
b10100100 (
b011010000 *
b110011101 +
#417
0#
#418
1#
b10101111 (
b011010001 *
b110011110 +
#419
0#
#420
1#
b10101110 (
b011010010 *
b110011111 +
#421
0#
#422
1#
b10101000 (
b011010011 *
b110100000 +
#423
0#
#424
1#
b10011100 (
b011010100 *
b110100001 +
#425
0#
#426
1#
b10001100 (
b011010101 *
b110100010 +
#427
0#
#428
1#
b01110111 (
b011010110 *
b110100011 +
#429
0#
#430
1#
b01100000 (
b011010111 *
b110100100 +
#431
0#
#432
1#
b01001100 (
b011011000 *
b110100101 +
#433
0#
#434
1#
b00111110 (
b011011001 *
b110100110 +
#435
0#
#436
1#
b00110011 (
b011011010 *
b110100111 +
#437
0#
#438
1#
b00101111 (
b011011011 *
b110101000 +
#439
0#
#440
1#
b011011100 *
b110101001 +
#441
0#
#442
1#
b00110010 (
b011011101 *
b110101010 +
#443
0#
#444
1#
b00110101 (
b011011110 *
b110101011 +
#445
0#
#446
1#
b00111110 (
b011011111 *
b110101100 +
#447
0#
#448
1#
b01001100 (
b011100000 *
b110101101 +
#449
0#
#450
1#
b01011100 (
b011100001 *
b110101110 +
#451
0#
#452
1#
b01110001 (
b011100010 *
b110101111 +
#453
0#
#454
1#
b10000010 (
b011100011 *
b110110000 +
#455
0#
#456
1#
b10010001 (
b011100100 *
b110110001 +
#457
0#
#458
1#
b10011101 (
b011100101 *
b110110010 +
#459
0#
#460
1#
b10100110 (
b011100110 *
b110110011 +
#461
0#
#462
1#
b10101100 (
b011100111 *
b110110100 +
#463
0#
#464
1#
b10101101 (
b011101000 *
b110110101 +
#465
0#
#466
1#
b10100110 (
b011101001 *
b110110110 +
#467
0#
#468
1#
b10011010 (
b011101010 *
b110110111 +
#469
0#
#470
1#
b10000100 (
b011101011 *
b110111000 +
#471
0#
#472
1#
b01101111 (
b011101100 *
b110111001 +
#473
0#
#474
1#
b01011001 (
b011101101 *
b110111010 +
#475
0#
#476
1#
b01000101 (
b011101110 *
b110111011 +
#477
0#
#478
1#
b00111000 (
b011101111 *
b110111100 +
#479
0#
#480
1#
b00110010 (
b011110000 *
b110111101 +
#481
0#
#482
1#
b00101110 (
b011110001 *
b110111110 +
#483
0#
#484
1#
b00101101 (
b011110010 *
b110111111 +
#485
0#
#486
1#
b00110011 (
b011110011 *
b111000000 +
#487
0#
#488
1#
b00111010 (
b011110100 *
b111000001 +
#489
0#
#490
1#
b01000111 (
b011110101 *
b111000010 +
#491
0#
#492
1#
b01010011 (
b011110110 *
b111000011 +
#493
0#
#494
1#
b01100111 (
b011110111 *
b111000100 +
#495
0#
#496
1#
b01111000 (
b011111000 *
b111000101 +
#497
0#
#498
1#
b10000101 (
b011111001 *
b111000110 +
#499
0#
#500
1#
b10010101 (
b011111010 *
b111000111 +
#501
0#
#502
1#
b10100011 (
b011111011 *
b111001000 +
#503
0#
#504
1#
b10101001 (
b011111100 *
b111001001 +
#505
0#
#506
1#
b10101100 (
b011111101 *
b111001010 +
#507
0#
#508
1#
b10101011 (
b011111110 *
b111001011 +
#509
0#
#510
1#
b10100011 (
b011111111 *
b111001100 +
#511
0#
#512
1#
b10010000 (
b100000000 *
b111001101 +
#513
0#
#514
1#
b01111101 (
b100000001 *
b111001110 +
#515
0#
#516
1#
b01101000 (
b100000010 *
b111001111 +
#517
0#
#518
1#
b01010001 (
b100000011 *
b111010000 +
#519
0#
#520
1#
b01000001 (
b100000100 *
b111010001 +
#521
0#
#522
1#
b00110100 (
b100000101 *
b111010010 +
#523
0#
#524
1#
b00101110 (
b100000110 *
b111010011 +
#525
0#
#526
1#
b00101001 (
b100000111 *
b111010100 +
#527
0#
#528
1#
b00101110 (
b100001000 *
b111010101 +
#529
0#
#530
1#
b00110101 (
b100001001 *
b111010110 +
#531
0#
#532
1#
b00111100 (
b100001010 *
b111010111 +
#533
0#
#534
1#
b01001011 (
b100001011 *
b111011000 +
#535
0#
#536
1#
b01011001 (
b100001100 *
b111011001 +
#537
0#
#538
1#
b01101011 (
b100001101 *
b111011010 +
#539
0#
#540
1#
b01111110 (
b100001110 *
b111011011 +
#541
0#
#542
1#
b10001110 (
b100001111 *
b111011100 +
#543
0#
#544
1#
b10011110 (
b100010000 *
b111011101 +
#545
0#
#546
1#
b10100101 (
b100010001 *
b111011110 +
#547
0#
#548
1#
b10101101 (
b100010010 *
b111011111 +
#549
0#
#550
1#
b100010011 *
b111100000 +
#551
0#
#552
1#
b10100111 (
b100010100 *
b111100001 +
#553
0#
#554
1#
b10011010 (
b100010101 *
b111100010 +
#555
0#
#556
1#
b10000111 (
b100010110 *
b111100011 +
#557
0#
#558
1#
b01110001 (
b100010111 *
b111100100 +
#559
0#
#560
1#
b01011110 (
b100011000 *
b111100101 +
#561
0#
#562
1#
b01001100 (
b100011001 *
b111100110 +
#563
0#
#564
1#
b00111100 (
b100011010 *
b111100111 +
#565
0#
#566
1#
b00110011 (
b100011011 *
b111101000 +
#567
0#
#568
1#
b00110000 (
b100011100 *
b111101001 +
#569
0#
#570
1#
b00101011 (
b100011101 *
b111101010 +
#571
0#
#572
1#
b00110001 (
b100011110 *
b111101011 +
#573
0#
#574
1#
b00110110 (
b100011111 *
b111101100 +
#575
0#
#576
1#
b01000010 (
b100100000 *
b111101101 +
#577
0#
#578
1#
b01001111 (
b100100001 *
b111101110 +
#579
0#
#580
1#
b01011110 (
b100100010 *
b111101111 +
#581
0#
#582
1#
b01110000 (
b100100011 *
b111110000 +
#583
0#
#584
1#
b10000010 (
b100100100 *
b111110001 +
#585
0#
#586
1#
b10010001 (
b100100101 *
b111110010 +
#587
0#
#588
1#
b10100000 (
b100100110 *
b111110011 +
#589
0#
#590
1#
b10100111 (
b100100111 *
b111110100 +
#591
0#
#592
1#
b10101101 (
b100101000 *
b111110101 +
#593
0#
#594
1#
b10101011 (
b100101001 *
b111110110 +
#595
0#
#596
1#
b10100110 (
b100101010 *
b111110111 +
#597
0#
#598
1#
b10010100 (
b100101011 *
b111111000 +
#599
0#
#600
1#
b10000101 (
b100101100 *
b111111001 +
#601
0#
#602
1#
b01101100 (
b100101101 *
b111111010 +
#603
0#
#604
1#
b01010110 (
b100101110 *
b111111011 +
#605
0#
#606
1#
b01000110 (
b100101111 *
b111111100 +
#607
0#
#608
1#
b00111010 (
b100110000 *
b111111101 +
#609
0#
#610
1#
b00101111 (
b100110001 *
b111111110 +
#611
0#
#612
1#
b100110010 *
b111111111 +
#613
0#
#614
1#
b00101100 (
b100110011 *
b000000000 +
#615
0#
#616
1#
b00110010 (
b100110100 *
b000000001 +
#617
0#
#618
1#
b00111011 (
b00111101 )
b100110101 *
b000000010 +
#619
0#
#620
1#
b01000111 (
b00101110 )
b100110110 *
b000000011 +
#621
0#
#622
1#
b01010100 (
b100110111 *
b000000100 +
#623
0#
#624
1#
b01100111 (
b00101111 )
b100111000 *
b000000101 +
#625
0#
#626
1#
b01110110 (
b00110100 )
b100111001 *
b000000110 +
#627
0#
#628
1#
b10000111 (
b00111010 )
b100111010 *
b000000111 +
#629
0#
#630
1#
b10011000 (
b01001001 )
b100111011 *
b000001000 +
#631
0#
#632
1#
b10100011 (
b01011001 )
b100111100 *
b000001001 +
#633
0#
#634
1#
b10101010 (
b01101010 )
b100111101 *
b000001010 +
#635
0#
#636
1#
b10101111 (
b01111011 )
b100111110 *
b000001011 +
#637
0#
#638
1#
b10101011 (
b10001010 )
b100111111 *
b000001100 +
#639
0#
#640
1#
b10100000 (
b10011010 )
b101000000 *
b000001101 +
#641
0#
#642
1#
b10001110 (
b10100011 )
b101000001 *
b000001110 +
#643
0#
#644
1#
b01111100 (
b10101010 )
b101000010 *
b000001111 +
#645
0#
#646
1#
b01101000 (
b101000011 *
b000010000 +
#647
0#
#648
1#
b01010000 (
b10101000 )
b101000100 *
b000010001 +
#649
0#
#650
1#
b01000001 (
b10011101 )
b101000101 *
b000010010 +
#651
0#
#652
1#
b00110100 (
b10001011 )
b101000110 *
b000010011 +
#653
0#
#654
1#
b00101110 (
b01110111 )
b101000111 *
b000010100 +
#655
0#
#656
1#
b00101101 (
b01011111 )
b101001000 *
b000010101 +
#657
0#
#658
1#
b00101111 (
b01001101 )
b101001001 *
b000010110 +
#659
0#
#660
1#
b00110011 (
b00111011 )
b101001010 *
b000010111 +
#661
0#
#662
1#
b00111011 (
b00110100 )
b101001011 *
b000011000 +
#663
0#
#664
1#
b01001100 (
b00101101 )
b101001100 *
b000011001 +
#665
0#
#666
1#
b01011001 (
b101001101 *
b000011010 +
#667
0#
#668
1#
b01101001 (
b00110001 )
b101001110 *
b000011011 +
#669
0#
#670
1#
b01111111 (
b00110110 )
b101001111 *
b000011100 +
#671
0#
#672
1#
b10001110 (
b01000001 )
b101010000 *
b000011101 +
#673
0#
#674
1#
b10011101 (
b01010000 )
b101010001 *
b000011110 +
#675
0#
#676
1#
b10100111 (
b01011111 )
b101010010 *
b000011111 +
#677
0#
#678
1#
b10101100 (
b01101111 )
b101010011 *
b000100000 +
#679
0#
#680
1#
b10101111 (
b10000100 )
b101010100 *
b000100001 +
#681
0#
#682
1#
b10101000 (
b10010000 )
b101010101 *
b000100010 +
#683
0#
#684
1#
b10011001 (
b10011101 )
b101010110 *
b000100011 +
#685
0#
#686
1#
b10001100 (
b10100101 )
b101010111 *
b000100100 +
#687
0#
#688
1#
b01110110 (
b10101010 )
b101011000 *
b000100101 +
#689
0#
#690
1#
b01100000 (
b10101100 )
b101011001 *
b000100110 +
#691
0#
#692
1#
b01001001 (
b10100010 )
b101011010 *
b000100111 +
#693
0#
#694
1#
b00111100 (
b10010110 )
b101011011 *
b000101000 +
#695
0#
#696
1#
b00110011 (
b10000011 )
b101011100 *
b000101001 +
#697
0#
#698
1#
b00101101 (
b01110000 )
b101011101 *
b000101010 +
#699
0#
#700
1#
b01010110 )
b101011110 *
b000101011 +
#701
0#
#702
1#
b00110000 (
b01000111 )
b101011111 *
b000101100 +
#703
0#
#704
1#
b00111000 (
b00111000 )
b101100000 *
b000101101 +
#705
0#
#706
1#
b01000011 (
b00110000 )
b101100001 *
b000101110 +
#707
0#
#708
1#
b01010001 (
b00101101 )
b101100010 *
b000101111 +
#709
0#
#710
1#
b01100000 (
b00101100 )
b101100011 *
b000110000 +
#711
0#
#712
1#
b01110100 (
b00110001 )
b101100100 *
b000110001 +
#713
0#
#714
1#
b10000100 (
b00111010 )
b101100101 *
b000110010 +
#715
0#
#716
1#
b10010101 (
b01000101 )
b101100110 *
b000110011 +
#717
0#
#718
1#
b10100001 (
b01010011 )
b101100111 *
b000110100 +
#719
0#
#720
1#
b10101010 (
b01100101 )
b101101000 *
b000110101 +
#721
0#
#722
1#
b10101110 (
b01110100 )
b101101001 *
b000110110 +
#723
0#
#724
1#
b10101100 (
b10000111 )
b101101010 *
b000110111 +
#725
0#
#726
1#
b10100111 (
b10010111 )
b101101011 *
b000111000 +
#727
0#
#728
1#
b10010111 (
b10100001 )
b101101100 *
b000111001 +
#729
0#
#730
1#
b10000100 (
b10100111 )
b101101101 *
b000111010 +
#731
0#
#732
1#
b01101111 (
b10101101 )
b101101110 *
b000111011 +
#733
0#
#734
1#
b01011011 (
b10101011 )
b101101111 *
b000111100 +
#735
0#
#736
1#
b01001001 (
b10100001 )
b101110000 *
b000111101 +
#737
0#
#738
1#
b00111001 (
b10010001 )
b101110001 *
b000111110 +
#739
0#
#740
1#
b00110010 (
b01111011 )
b101110010 *
b000111111 +
#741
0#
#742
1#
b00101110 (
b01101010 )
b101110011 *
b001000000 +
#743
0#
#744
1#
b01010000 )
b101110100 *
b001000001 +
#745
0#
#746
1#
b00110000 (
b01000010 )
b101110101 *
b001000010 +
#747
0#
#748
1#
b00111000 (
b00110110 )
b101110110 *
b001000011 +
#749
0#
#750
1#
b01000011 (
b00101110 )
b101110111 *
b001000100 +
#751
0#
#752
1#
b01010011 (
b00101101 )
b101111000 *
b001000101 +
#753
0#
#754
1#
b01100010 (
b101111001 *
b001000110 +
#755
0#
#756
1#
b01110111 (
b00110010 )
b101111010 *
b001000111 +
#757
0#
#758
1#
b10000110 (
b00111100 )
b101111011 *
b001001000 +
#759
0#
#760
1#
b10010100 (
b01001001 )
b101111100 *
b001001001 +
#761
0#
#762
1#
b10100001 (
b01010111 )
b101111101 *
b001001010 +
#763
0#
#764
1#
b10101010 (
b01101000 )
b101111110 *
b001001011 +
#765
0#
#766
1#
b10101111 (
b01111100 )
b101111111 *
b001001100 +
#767
0#
#768
1#
b10101011 (
b10001001 )
b110000000 *
b001001101 +
#769
0#
#770
1#
b10100001 (
b10011001 )
b110000001 *
b001001110 +
#771
0#
#772
1#
b10010000 (
b10100100 )
b110000010 *
b001001111 +
#773
0#
#774
1#
b01111111 (
b10101000 )
b110000011 *
b001010000 +
#775
0#
#776
1#
b01101000 (
b10101110 )
b110000100 *
b001010001 +
#777
0#
#778
1#
b01010010 (
b10101001 )
b110000101 *
b001010010 +
#779
0#
#780
1#
b01000101 (
b10011110 )
b110000110 *
b001010011 +
#781
0#
#782
1#
b00110101 (
b10001110 )
b110000111 *
b001010100 +
#783
0#
#784
1#
b00110000 (
b01111010 )
b110001000 *
b001010101 +
#785
0#
#786
1#
b00101011 (
b01100010 )
b110001001 *
b001010110 +
#787
0#
#788
1#
b00101110 (
b01001110 )
b110001010 *
b001010111 +
#789
0#
